docs/conf.py
wandb_callbacks/__init__.py
wandb_callbacks/tensorflow.py
wandb_callbacks/utils.py
wandb_callbacks-0.2.1.dist-info/LICENSE
wandb_callbacks-0.2.1.dist-info/METADATA
wandb_callbacks-0.2.1.dist-info/WHEEL
wandb_callbacks-0.2.1.dist-info/top_level.txt
wandb_callbacks-0.2.1.dist-info/RECORD
