Metadata-Version: 2.1
Name: wandb-callbacks
Version: 0.2.1
Summary: Additional custom callbacks for Weights & Biases
Home-page: https://github.com/FabianGroeger96/wandb-callbacks
Author: Fabian Groeger
Author-email: fabian.groeger@bluewin.ch
License: UNKNOWN
Keywords: wandb,keras,tensorflow,callbacks
Platform: UNKNOWN
Classifier: Development Status :: 1 - Planning
Classifier: Intended Audience :: Science/Research
Classifier: License :: OSI Approved :: BSD License
Classifier: Operating System :: POSIX :: Linux
Classifier: Programming Language :: Python :: 2
Classifier: Programming Language :: Python :: 2.7
Classifier: Programming Language :: Python :: 3
Classifier: Programming Language :: Python :: 3.4
Classifier: Programming Language :: Python :: 3.5
